converter/__init__.py
converter/currency.py
converter/distance.py
converter/mass.py
converter/temperature.py
ultimate_unit_converter-0.1.0.dist-info/METADATA
ultimate_unit_converter-0.1.0.dist-info/WHEEL
ultimate_unit_converter-0.1.0.dist-info/top_level.txt
ultimate_unit_converter-0.1.0.dist-info/RECORD
