Metadata-Version: 2.1
Name: ultimate-unit-converter
Version: 0.1.0
Summary: A package to convert units of distance, temperature, mass, and currency.
Author: Nizarus.py
Author-email: nizar.chawechy.1618@gmail.com
Classifier: Programming Language :: Python :: 3
Classifier: License :: OSI Approved :: MIT License
Classifier: Operating System :: OS Independent
Requires-Python: >=3.6
Requires-Dist: requests
Requires-Dist: string-color
